jwplatform/__init__.py
jwplatform/client.py
jwplatform/errors.py
jwplatform/response.py
jwplatform/upload.py
jwplatform/version.py
jwplatform/v1/__init__.py
jwplatform/v1/client.py
jwplatform/v1/errors.py
jwplatform/v1/resource.py
tests/v1/__init__.py
tests/v1/test_build_request.py
tests/v1/test_errors.py
tests/v1/test_init.py
tests/v1/test_resource.py
jwplatform-2.2.2.dist-info/LICENSE
jwplatform-2.2.2.dist-info/METADATA
jwplatform-2.2.2.dist-info/WHEEL
jwplatform-2.2.2.dist-info/top_level.txt
jwplatform-2.2.2.dist-info/RECORD
