Metadata-Version: 2.1
Name: jwplatform
Version: 2.2.2
Summary: A Python client library for accessing JW Platform API
Home-page: https://github.com/jwplayer/jwplatform-py
Author: Kamil Sindi
Author-email: support@jwplayer.com
License: MIT
Keywords: JW Platform,api,client,JW Player
Platform: UNKNOWN
Classifier: Development Status :: 5 - Production/Stable
Classifier: Intended Audience :: Developers
Classifier: Topic :: Software Development :: Libraries :: Python Modules
Classifier: License :: OSI Approved :: MIT License
Classifier: Programming Language :: Python
Classifier: Programming Language :: Python :: 3
Classifier: Programming Language :: Python :: 3.5
Classifier: Programming Language :: Python :: 3.6
Classifier: Programming Language :: Python :: 3.7
Classifier: Programming Language :: Python :: 3.8
Classifier: Programming Language :: Python :: 3 :: Only
License-File: LICENSE
Requires-Dist: requests (>=2.24.0)
Requires-Dist: neterr (~=1.1.1)
